{
  "code": "sh.512820",
  "name": "汇添富中证银行ETF",
  "industry": "",
  "area": "",
  "updated_at": "2026-02-10 18:48:51",
  "kline": [
    {
      "date": "2026-01-05",
      "open": 1.445,
      "high": 1.453,
      "low": 1.435,
      "close": 1.44,
      "volume": 79921000
    },
    {
      "date": "2026-01-06",
      "open": 1.436,
      "high": 1.448,
      "low": 1.431,
      "close": 1.447,
      "volume": 73012201
    },
    {
      "date": "2026-01-07",
      "open": 1.446,
      "high": 1.451,
      "low": 1.436,
      "close": 1.439,
      "volume": 69715900
    },
    {
      "date": "2026-01-08",
      "open": 1.439,
      "high": 1.439,
      "low": 1.42,
      "close": 1.426,
      "volume": 61762400
    },
    {
      "date": "2026-01-09",
      "open": 1.422,
      "high": 1.426,
      "low": 1.415,
      "close": 1.418,
      "volume": 74267100
    },
    {
      "date": "2026-01-12",
      "open": 1.417,
      "high": 1.425,
      "low": 1.41,
      "close": 1.424,
      "volume": 41106761
    },
    {
      "date": "2026-01-13",
      "open": 1.421,
      "high": 1.442,
      "low": 1.421,
      "close": 1.432,
      "volume": 66966362
    },
    {
      "date": "2026-01-14",
      "open": 1.43,
      "high": 1.431,
      "low": 1.408,
      "close": 1.413,
      "volume": 96711362
    },
    {
      "date": "2026-01-15",
      "open": 1.409,
      "high": 1.41,
      "low": 1.396,
      "close": 1.398,
      "volume": 65481000
    },
    {
      "date": "2026-01-16",
      "open": 1.398,
      "high": 1.403,
      "low": 1.378,
      "close": 1.381,
      "volume": 62641700
    },
    {
      "date": "2026-01-19",
      "open": 1.381,
      "high": 1.385,
      "low": 1.371,
      "close": 1.376,
      "volume": 55711100
    },
    {
      "date": "2026-01-20",
      "open": 1.376,
      "high": 1.388,
      "low": 1.37,
      "close": 1.387,
      "volume": 83825043
    },
    {
      "date": "2026-01-21",
      "open": 1.385,
      "high": 1.391,
      "low": 1.361,
      "close": 1.366,
      "volume": 105295100
    },
    {
      "date": "2026-01-22",
      "open": 1.363,
      "high": 1.375,
      "low": 1.356,
      "close": 1.357,
      "volume": 90800682
    },
    {
      "date": "2026-01-23",
      "open": 1.357,
      "high": 1.362,
      "low": 1.342,
      "close": 1.345,
      "volume": 105456300
    },
    {
      "date": "2026-01-26",
      "open": 1.343,
      "high": 1.36,
      "low": 1.338,
      "close": 1.35,
      "volume": 74841500
    },
    {
      "date": "2026-01-27",
      "open": 1.349,
      "high": 1.365,
      "low": 1.347,
      "close": 1.349,
      "volume": 71152400
    },
    {
      "date": "2026-01-28",
      "open": 1.347,
      "high": 1.357,
      "low": 1.339,
      "close": 1.342,
      "volume": 67432400
    },
    {
      "date": "2026-01-29",
      "open": 1.342,
      "high": 1.363,
      "low": 1.332,
      "close": 1.361,
      "volume": 64289400
    },
    {
      "date": "2026-01-30",
      "open": 1.361,
      "high": 1.374,
      "low": 1.355,
      "close": 1.355,
      "volume": 66851900
    },
    {
      "date": "2026-02-02",
      "open": 1.356,
      "high": 1.377,
      "low": 1.356,
      "close": 1.36,
      "volume": 106978200
    },
    {
      "date": "2026-02-03",
      "open": 1.358,
      "high": 1.36,
      "low": 1.342,
      "close": 1.348,
      "volume": 75312000
    },
    {
      "date": "2026-02-04",
      "open": 1.347,
      "high": 1.366,
      "low": 1.345,
      "close": 1.365,
      "volume": 77726400
    },
    {
      "date": "2026-02-05",
      "open": 1.368,
      "high": 1.391,
      "low": 1.366,
      "close": 1.388,
      "volume": 106273000
    },
    {
      "date": "2026-02-06",
      "open": 1.385,
      "high": 1.395,
      "low": 1.376,
      "close": 1.383,
      "volume": 75156300
    },
    {
      "date": "2026-02-09",
      "open": 1.379,
      "high": 1.39,
      "low": 1.374,
      "close": 1.388,
      "volume": 71626300
    },
    {
      "date": "2026-02-10",
      "open": 1.387,
      "high": 1.396,
      "low": 1.387,
      "close": 1.392,
      "volume": 61869600
    }
  ]
}