{
  "code": "sh.562000",
  "name": "华宝中证A100ETF",
  "industry": "",
  "area": "",
  "updated_at": "2026-02-09 20:33:38",
  "kline": [
    {
      "date": "2026-01-05",
      "open": 0.59,
      "high": 0.603,
      "low": 0.59,
      "close": 0.603,
      "volume": 46870000
    },
    {
      "date": "2026-01-06",
      "open": 0.603,
      "high": 0.612,
      "low": 0.603,
      "close": 0.611,
      "volume": 18840500
    },
    {
      "date": "2026-01-07",
      "open": 0.611,
      "high": 0.614,
      "low": 0.607,
      "close": 0.611,
      "volume": 19196500
    },
    {
      "date": "2026-01-08",
      "open": 0.611,
      "high": 0.611,
      "low": 0.604,
      "close": 0.607,
      "volume": 38023200
    },
    {
      "date": "2026-01-09",
      "open": 0.606,
      "high": 0.611,
      "low": 0.604,
      "close": 0.609,
      "volume": 13810900
    },
    {
      "date": "2026-01-12",
      "open": 0.613,
      "high": 0.614,
      "low": 0.607,
      "close": 0.611,
      "volume": 13669100
    },
    {
      "date": "2026-01-13",
      "open": 0.613,
      "high": 0.62,
      "low": 0.606,
      "close": 0.609,
      "volume": 20657400
    },
    {
      "date": "2026-01-14",
      "open": 0.61,
      "high": 0.617,
      "low": 0.603,
      "close": 0.608,
      "volume": 26068300
    },
    {
      "date": "2026-01-15",
      "open": 0.607,
      "high": 0.612,
      "low": 0.606,
      "close": 0.61,
      "volume": 67704500
    },
    {
      "date": "2026-01-16",
      "open": 0.612,
      "high": 0.617,
      "low": 0.606,
      "close": 0.609,
      "volume": 12445500
    },
    {
      "date": "2026-01-19",
      "open": 0.609,
      "high": 0.613,
      "low": 0.607,
      "close": 0.609,
      "volume": 15078300
    },
    {
      "date": "2026-01-20",
      "open": 0.61,
      "high": 0.611,
      "low": 0.602,
      "close": 0.608,
      "volume": 24809800
    },
    {
      "date": "2026-01-21",
      "open": 0.607,
      "high": 0.614,
      "low": 0.607,
      "close": 0.609,
      "volume": 14209300
    },
    {
      "date": "2026-01-22",
      "open": 0.61,
      "high": 0.614,
      "low": 0.602,
      "close": 0.607,
      "volume": 14928700
    },
    {
      "date": "2026-01-23",
      "open": 0.608,
      "high": 0.609,
      "low": 0.603,
      "close": 0.604,
      "volume": 9596700
    },
    {
      "date": "2026-01-26",
      "open": 0.607,
      "high": 0.612,
      "low": 0.603,
      "close": 0.605,
      "volume": 9795600
    },
    {
      "date": "2026-01-27",
      "open": 0.605,
      "high": 0.609,
      "low": 0.6,
      "close": 0.605,
      "volume": 6526700
    },
    {
      "date": "2026-01-28",
      "open": 0.606,
      "high": 0.611,
      "low": 0.605,
      "close": 0.609,
      "volume": 14124200
    },
    {
      "date": "2026-01-29",
      "open": 0.61,
      "high": 0.618,
      "low": 0.606,
      "close": 0.617,
      "volume": 15586200
    },
    {
      "date": "2026-01-30",
      "open": 0.613,
      "high": 0.613,
      "low": 0.597,
      "close": 0.607,
      "volume": 18400200
    },
    {
      "date": "2026-02-02",
      "open": 0.603,
      "high": 0.605,
      "low": 0.588,
      "close": 0.589,
      "volume": 10136700
    },
    {
      "date": "2026-02-03",
      "open": 0.589,
      "high": 0.597,
      "low": 0.587,
      "close": 0.597,
      "volume": 16361600
    },
    {
      "date": "2026-02-04",
      "open": 0.6,
      "high": 0.604,
      "low": 0.594,
      "close": 0.603,
      "volume": 7637500
    },
    {
      "date": "2026-02-05",
      "open": 0.602,
      "high": 0.602,
      "low": 0.594,
      "close": 0.598,
      "volume": 16576200
    },
    {
      "date": "2026-02-06",
      "open": 0.594,
      "high": 0.6,
      "low": 0.59,
      "close": 0.596,
      "volume": 8316600
    },
    {
      "date": "2026-02-09",
      "open": 0.6,
      "high": 0.606,
      "low": 0.6,
      "close": 0.606,
      "volume": 5952500
    }
  ]
}