{
  "code": "sh.520830",
  "name": "华泰柏瑞南方东英沙特ETF",
  "industry": "",
  "area": "",
  "updated_at": "2026-02-09 20:29:33",
  "kline": [
    {
      "date": "2026-01-05",
      "open": 0.903,
      "high": 0.906,
      "low": 0.903,
      "close": 0.905,
      "volume": 65657845
    },
    {
      "date": "2026-01-06",
      "open": 0.901,
      "high": 0.904,
      "low": 0.901,
      "close": 0.903,
      "volume": 77084300
    },
    {
      "date": "2026-01-07",
      "open": 0.908,
      "high": 0.916,
      "low": 0.907,
      "close": 0.914,
      "volume": 161434880
    },
    {
      "date": "2026-01-08",
      "open": 0.91,
      "high": 0.911,
      "low": 0.904,
      "close": 0.904,
      "volume": 68361000
    },
    {
      "date": "2026-01-09",
      "open": 0.908,
      "high": 0.911,
      "low": 0.907,
      "close": 0.91,
      "volume": 93651700
    },
    {
      "date": "2026-01-12",
      "open": 0.912,
      "high": 0.914,
      "low": 0.908,
      "close": 0.91,
      "volume": 81946300
    },
    {
      "date": "2026-01-13",
      "open": 0.918,
      "high": 0.929,
      "low": 0.916,
      "close": 0.927,
      "volume": 172793100
    },
    {
      "date": "2026-01-14",
      "open": 0.933,
      "high": 0.944,
      "low": 0.928,
      "close": 0.939,
      "volume": 246962200
    },
    {
      "date": "2026-01-15",
      "open": 0.937,
      "high": 0.937,
      "low": 0.926,
      "close": 0.926,
      "volume": 124366900
    },
    {
      "date": "2026-01-16",
      "open": 0.921,
      "high": 0.924,
      "low": 0.918,
      "close": 0.919,
      "volume": 74499700
    },
    {
      "date": "2026-01-19",
      "open": 0.92,
      "high": 0.923,
      "low": 0.918,
      "close": 0.918,
      "volume": 46162200
    },
    {
      "date": "2026-01-20",
      "open": 0.921,
      "high": 0.922,
      "low": 0.918,
      "close": 0.919,
      "volume": 45031900
    },
    {
      "date": "2026-01-21",
      "open": 0.919,
      "high": 0.919,
      "low": 0.915,
      "close": 0.915,
      "volume": 38616400
    },
    {
      "date": "2026-01-22",
      "open": 0.92,
      "high": 0.928,
      "low": 0.919,
      "close": 0.926,
      "volume": 87126100
    },
    {
      "date": "2026-01-23",
      "open": 0.933,
      "high": 0.937,
      "low": 0.932,
      "close": 0.933,
      "volume": 94685100
    },
    {
      "date": "2026-01-26",
      "open": 0.938,
      "high": 0.949,
      "low": 0.938,
      "close": 0.945,
      "volume": 126871500
    },
    {
      "date": "2026-01-27",
      "open": 0.946,
      "high": 0.954,
      "low": 0.946,
      "close": 0.951,
      "volume": 106652900
    },
    {
      "date": "2026-01-28",
      "open": 0.96,
      "high": 1.005,
      "low": 0.957,
      "close": 0.97,
      "volume": 969377590
    },
    {
      "date": "2026-01-29",
      "open": 0.977,
      "high": 0.992,
      "low": 0.962,
      "close": 0.975,
      "volume": 860507318
    },
    {
      "date": "2026-01-30",
      "open": 0.975,
      "high": 1.03,
      "low": 0.955,
      "close": 0.956,
      "volume": 2179781598
    },
    {
      "date": "2026-02-02",
      "open": 0.939,
      "high": 0.946,
      "low": 0.927,
      "close": 0.928,
      "volume": 339908917
    },
    {
      "date": "2026-02-03",
      "open": 0.944,
      "high": 0.953,
      "low": 0.944,
      "close": 0.947,
      "volume": 247069904
    },
    {
      "date": "2026-02-04",
      "open": 0.944,
      "high": 0.948,
      "low": 0.942,
      "close": 0.945,
      "volume": 111395046
    },
    {
      "date": "2026-02-05",
      "open": 0.95,
      "high": 0.952,
      "low": 0.945,
      "close": 0.947,
      "volume": 96958452
    },
    {
      "date": "2026-02-06",
      "open": 0.936,
      "high": 0.942,
      "low": 0.931,
      "close": 0.937,
      "volume": 123012800
    },
    {
      "date": "2026-02-09",
      "open": 0.942,
      "high": 0.944,
      "low": 0.939,
      "close": 0.941,
      "volume": 60316892
    }
  ]
}