{
  "code": "sh.603203",
  "name": "快克智能",
  "industry": "",
  "area": "",
  "updated_at": "2026-02-09 21:11:01",
  "kline": [
    {
      "date": "2025-12-11",
      "open": 30.57,
      "high": 30.65,
      "low": 30.1,
      "close": 30.19,
      "volume": 1046800
    },
    {
      "date": "2025-12-12",
      "open": 30.3,
      "high": 30.4,
      "low": 29.8,
      "close": 30.3,
      "volume": 1123818
    },
    {
      "date": "2025-12-15",
      "open": 30.3,
      "high": 31.06,
      "low": 30.0,
      "close": 30.69,
      "volume": 2297100
    },
    {
      "date": "2025-12-16",
      "open": 30.66,
      "high": 30.75,
      "low": 29.79,
      "close": 30.32,
      "volume": 2449106
    },
    {
      "date": "2025-12-17",
      "open": 30.0,
      "high": 31.2,
      "low": 29.53,
      "close": 31.0,
      "volume": 3077659
    },
    {
      "date": "2025-12-18",
      "open": 30.49,
      "high": 31.2,
      "low": 30.15,
      "close": 30.26,
      "volume": 2408519
    },
    {
      "date": "2025-12-19",
      "open": 30.3,
      "high": 30.66,
      "low": 30.28,
      "close": 30.5,
      "volume": 1755273
    },
    {
      "date": "2025-12-22",
      "open": 30.51,
      "high": 32.64,
      "low": 30.51,
      "close": 32.48,
      "volume": 5235343
    },
    {
      "date": "2025-12-23",
      "open": 32.78,
      "high": 35.73,
      "low": 32.49,
      "close": 35.73,
      "volume": 11058940
    },
    {
      "date": "2025-12-24",
      "open": 37.55,
      "high": 38.99,
      "low": 36.83,
      "close": 37.75,
      "volume": 19629585
    },
    {
      "date": "2025-12-25",
      "open": 37.0,
      "high": 38.72,
      "low": 37.0,
      "close": 38.42,
      "volume": 12524842
    },
    {
      "date": "2025-12-26",
      "open": 38.14,
      "high": 38.54,
      "low": 36.98,
      "close": 37.48,
      "volume": 9695134
    },
    {
      "date": "2025-12-29",
      "open": 37.58,
      "high": 37.88,
      "low": 36.0,
      "close": 36.78,
      "volume": 7766415
    },
    {
      "date": "2025-12-30",
      "open": 36.34,
      "high": 38.2,
      "low": 36.34,
      "close": 37.43,
      "volume": 6925933
    },
    {
      "date": "2025-12-31",
      "open": 37.44,
      "high": 38.1,
      "low": 36.52,
      "close": 36.61,
      "volume": 4280050
    },
    {
      "date": "2026-01-05",
      "open": 36.6,
      "high": 37.2,
      "low": 36.41,
      "close": 36.77,
      "volume": 4805859
    },
    {
      "date": "2026-01-06",
      "open": 36.8,
      "high": 37.14,
      "low": 36.43,
      "close": 36.73,
      "volume": 4259396
    },
    {
      "date": "2026-01-07",
      "open": 36.73,
      "high": 37.63,
      "low": 36.5,
      "close": 37.23,
      "volume": 5314706
    },
    {
      "date": "2026-01-08",
      "open": 37.51,
      "high": 37.68,
      "low": 36.23,
      "close": 36.68,
      "volume": 5487846
    },
    {
      "date": "2026-01-09",
      "open": 36.09,
      "high": 36.75,
      "low": 36.09,
      "close": 36.68,
      "volume": 3758564
    },
    {
      "date": "2026-01-12",
      "open": 36.75,
      "high": 36.92,
      "low": 36.15,
      "close": 36.68,
      "volume": 4142096
    },
    {
      "date": "2026-01-13",
      "open": 36.58,
      "high": 36.88,
      "low": 35.81,
      "close": 36.1,
      "volume": 4062904
    },
    {
      "date": "2026-01-14",
      "open": 36.38,
      "high": 36.91,
      "low": 35.63,
      "close": 36.22,
      "volume": 5542600
    },
    {
      "date": "2026-01-15",
      "open": 36.05,
      "high": 37.18,
      "low": 36.0,
      "close": 37.15,
      "volume": 5942962
    },
    {
      "date": "2026-01-16",
      "open": 37.39,
      "high": 38.5,
      "low": 36.7,
      "close": 38.04,
      "volume": 6570840
    },
    {
      "date": "2026-01-19",
      "open": 38.01,
      "high": 39.21,
      "low": 37.71,
      "close": 38.81,
      "volume": 5710911
    },
    {
      "date": "2026-01-20",
      "open": 38.43,
      "high": 38.43,
      "low": 36.72,
      "close": 37.12,
      "volume": 6130062
    },
    {
      "date": "2026-01-21",
      "open": 36.8,
      "high": 40.83,
      "low": 36.5,
      "close": 40.83,
      "volume": 7659386
    },
    {
      "date": "2026-01-22",
      "open": 41.5,
      "high": 41.99,
      "low": 39.5,
      "close": 40.32,
      "volume": 8651967
    },
    {
      "date": "2026-01-23",
      "open": 40.71,
      "high": 41.4,
      "low": 39.61,
      "close": 40.0,
      "volume": 4852267
    },
    {
      "date": "2026-01-26",
      "open": 39.75,
      "high": 40.27,
      "low": 39.16,
      "close": 39.34,
      "volume": 4027263
    },
    {
      "date": "2026-01-27",
      "open": 39.03,
      "high": 39.38,
      "low": 37.59,
      "close": 39.02,
      "volume": 5390482
    },
    {
      "date": "2026-01-28",
      "open": 38.84,
      "high": 39.19,
      "low": 37.85,
      "close": 38.17,
      "volume": 3989801
    },
    {
      "date": "2026-01-29",
      "open": 38.01,
      "high": 38.2,
      "low": 36.42,
      "close": 36.58,
      "volume": 4859108
    },
    {
      "date": "2026-01-30",
      "open": 36.12,
      "high": 38.3,
      "low": 36.0,
      "close": 37.7,
      "volume": 4607862
    },
    {
      "date": "2026-02-02",
      "open": 37.5,
      "high": 38.22,
      "low": 36.58,
      "close": 36.66,
      "volume": 3227223
    },
    {
      "date": "2026-02-03",
      "open": 37.1,
      "high": 38.48,
      "low": 36.95,
      "close": 38.36,
      "volume": 4187051
    },
    {
      "date": "2026-02-04",
      "open": 38.0,
      "high": 38.28,
      "low": 36.81,
      "close": 37.15,
      "volume": 3650294
    },
    {
      "date": "2026-02-05",
      "open": 36.81,
      "high": 37.06,
      "low": 36.0,
      "close": 36.13,
      "volume": 2746308
    },
    {
      "date": "2026-02-06",
      "open": 36.0,
      "high": 37.16,
      "low": 35.86,
      "close": 36.51,
      "volume": 2192160
    },
    {
      "date": "2026-02-09",
      "open": 37.32,
      "high": 38.3,
      "low": 37.32,
      "close": 37.87,
      "volume": 3673209
    }
  ]
}