{
  "code": "sh.605365",
  "name": "立达信",
  "industry": "",
  "area": "",
  "updated_at": "2026-02-10 18:35:05",
  "kline": [
    {
      "date": "2025-12-11",
      "open": 20.39,
      "high": 21.5,
      "low": 20.25,
      "close": 21.1,
      "volume": 8383810
    },
    {
      "date": "2025-12-12",
      "open": 21.15,
      "high": 21.36,
      "low": 19.07,
      "close": 19.95,
      "volume": 11680758
    },
    {
      "date": "2025-12-15",
      "open": 19.89,
      "high": 20.2,
      "low": 19.36,
      "close": 19.99,
      "volume": 8050636
    },
    {
      "date": "2025-12-16",
      "open": 19.9,
      "high": 20.1,
      "low": 19.3,
      "close": 20.0,
      "volume": 5394000
    },
    {
      "date": "2025-12-17",
      "open": 20.14,
      "high": 22.0,
      "low": 20.01,
      "close": 22.0,
      "volume": 17319132
    },
    {
      "date": "2025-12-18",
      "open": 22.62,
      "high": 24.2,
      "low": 22.62,
      "close": 24.2,
      "volume": 19876851
    },
    {
      "date": "2025-12-19",
      "open": 25.1,
      "high": 26.61,
      "low": 24.3,
      "close": 26.01,
      "volume": 28088649
    },
    {
      "date": "2025-12-22",
      "open": 25.18,
      "high": 27.51,
      "low": 25.13,
      "close": 27.03,
      "volume": 20888048
    },
    {
      "date": "2025-12-23",
      "open": 26.83,
      "high": 28.2,
      "low": 26.3,
      "close": 27.12,
      "volume": 17575425
    },
    {
      "date": "2025-12-24",
      "open": 27.65,
      "high": 28.5,
      "low": 27.12,
      "close": 28.15,
      "volume": 14213136
    },
    {
      "date": "2025-12-25",
      "open": 28.3,
      "high": 28.88,
      "low": 26.55,
      "close": 27.82,
      "volume": 15921220
    },
    {
      "date": "2025-12-26",
      "open": 27.27,
      "high": 28.01,
      "low": 25.07,
      "close": 27.32,
      "volume": 20264033
    },
    {
      "date": "2025-12-29",
      "open": 27.87,
      "high": 28.96,
      "low": 26.6,
      "close": 28.0,
      "volume": 17933900
    },
    {
      "date": "2025-12-30",
      "open": 27.26,
      "high": 28.09,
      "low": 25.81,
      "close": 25.84,
      "volume": 14278700
    },
    {
      "date": "2025-12-31",
      "open": 24.65,
      "high": 26.58,
      "low": 24.4,
      "close": 26.46,
      "volume": 13352345
    },
    {
      "date": "2026-01-05",
      "open": 26.34,
      "high": 27.05,
      "low": 26.03,
      "close": 26.3,
      "volume": 7272733
    },
    {
      "date": "2026-01-06",
      "open": 26.5,
      "high": 26.95,
      "low": 25.84,
      "close": 26.88,
      "volume": 7533250
    },
    {
      "date": "2026-01-07",
      "open": 27.07,
      "high": 27.49,
      "low": 26.51,
      "close": 27.49,
      "volume": 5094800
    },
    {
      "date": "2026-01-08",
      "open": 27.98,
      "high": 28.05,
      "low": 25.21,
      "close": 25.5,
      "volume": 13681700
    },
    {
      "date": "2026-01-09",
      "open": 25.5,
      "high": 25.5,
      "low": 24.3,
      "close": 25.27,
      "volume": 6261860
    },
    {
      "date": "2026-01-12",
      "open": 25.49,
      "high": 25.49,
      "low": 24.3,
      "close": 24.47,
      "volume": 6565833
    },
    {
      "date": "2026-01-13",
      "open": 24.57,
      "high": 25.3,
      "low": 24.35,
      "close": 24.71,
      "volume": 6818500
    },
    {
      "date": "2026-01-14",
      "open": 24.49,
      "high": 24.85,
      "low": 24.01,
      "close": 24.35,
      "volume": 4986700
    },
    {
      "date": "2026-01-15",
      "open": 24.37,
      "high": 26.71,
      "low": 24.28,
      "close": 26.11,
      "volume": 10835400
    },
    {
      "date": "2026-01-16",
      "open": 26.19,
      "high": 26.35,
      "low": 24.9,
      "close": 25.63,
      "volume": 6737890
    },
    {
      "date": "2026-01-19",
      "open": 25.65,
      "high": 27.11,
      "low": 25.22,
      "close": 26.88,
      "volume": 9548400
    },
    {
      "date": "2026-01-20",
      "open": 26.62,
      "high": 27.24,
      "low": 26.25,
      "close": 26.84,
      "volume": 5685176
    },
    {
      "date": "2026-01-21",
      "open": 26.58,
      "high": 27.09,
      "low": 26.51,
      "close": 26.9,
      "volume": 5467560
    },
    {
      "date": "2026-01-22",
      "open": 26.88,
      "high": 27.37,
      "low": 24.31,
      "close": 24.33,
      "volume": 12184827
    },
    {
      "date": "2026-01-23",
      "open": 23.41,
      "high": 23.97,
      "low": 21.9,
      "close": 21.91,
      "volume": 23163105
    },
    {
      "date": "2026-01-26",
      "open": 21.5,
      "high": 21.96,
      "low": 21.24,
      "close": 21.51,
      "volume": 12982881
    },
    {
      "date": "2026-01-27",
      "open": 21.41,
      "high": 21.42,
      "low": 20.51,
      "close": 20.77,
      "volume": 9335000
    },
    {
      "date": "2026-01-28",
      "open": 20.7,
      "high": 20.91,
      "low": 20.31,
      "close": 20.56,
      "volume": 8240200
    },
    {
      "date": "2026-01-29",
      "open": 20.38,
      "high": 20.45,
      "low": 19.9,
      "close": 19.99,
      "volume": 7657200
    },
    {
      "date": "2026-01-30",
      "open": 19.98,
      "high": 20.28,
      "low": 19.74,
      "close": 20.11,
      "volume": 7068500
    },
    {
      "date": "2026-02-02",
      "open": 20.11,
      "high": 20.13,
      "low": 19.75,
      "close": 19.75,
      "volume": 4796300
    },
    {
      "date": "2026-02-03",
      "open": 19.9,
      "high": 21.18,
      "low": 19.77,
      "close": 20.48,
      "volume": 10129413
    },
    {
      "date": "2026-02-04",
      "open": 20.48,
      "high": 20.67,
      "low": 20.25,
      "close": 20.63,
      "volume": 4442340
    },
    {
      "date": "2026-02-05",
      "open": 20.58,
      "high": 20.97,
      "low": 20.38,
      "close": 20.62,
      "volume": 5101203
    },
    {
      "date": "2026-02-06",
      "open": 20.41,
      "high": 20.9,
      "low": 20.35,
      "close": 20.6,
      "volume": 5323683
    },
    {
      "date": "2026-02-09",
      "open": 20.75,
      "high": 20.77,
      "low": 20.25,
      "close": 20.54,
      "volume": 4573000
    },
    {
      "date": "2026-02-10",
      "open": 20.55,
      "high": 20.62,
      "low": 20.28,
      "close": 20.3,
      "volume": 3775100
    }
  ]
}