{
  "code": "sz.002329",
  "name": "皇氏集团",
  "industry": "",
  "area": "",
  "updated_at": "2026-02-10 18:42:34",
  "kline": [
    {
      "date": "2025-12-11",
      "open": 4.09,
      "high": 4.13,
      "low": 3.88,
      "close": 3.95,
      "volume": 82168371
    },
    {
      "date": "2025-12-12",
      "open": 3.97,
      "high": 4.29,
      "low": 3.75,
      "close": 3.78,
      "volume": 116215138
    },
    {
      "date": "2025-12-15",
      "open": 3.75,
      "high": 4.16,
      "low": 3.74,
      "close": 4.16,
      "volume": 64324270
    },
    {
      "date": "2025-12-16",
      "open": 4.58,
      "high": 4.58,
      "low": 4.58,
      "close": 4.58,
      "volume": 44131880
    },
    {
      "date": "2025-12-17",
      "open": 4.4,
      "high": 4.45,
      "low": 4.12,
      "close": 4.12,
      "volume": 178651367
    },
    {
      "date": "2025-12-18",
      "open": 4.05,
      "high": 4.53,
      "low": 3.99,
      "close": 4.53,
      "volume": 141617286
    },
    {
      "date": "2025-12-19",
      "open": 4.49,
      "high": 4.84,
      "low": 4.31,
      "close": 4.58,
      "volume": 245946972
    },
    {
      "date": "2025-12-22",
      "open": 4.58,
      "high": 4.64,
      "low": 4.4,
      "close": 4.45,
      "volume": 150570271
    },
    {
      "date": "2025-12-23",
      "open": 4.77,
      "high": 4.9,
      "low": 4.44,
      "close": 4.45,
      "volume": 190705258
    },
    {
      "date": "2025-12-24",
      "open": 4.38,
      "high": 4.6,
      "low": 4.24,
      "close": 4.57,
      "volume": 157939888
    },
    {
      "date": "2025-12-25",
      "open": 4.53,
      "high": 4.53,
      "low": 4.33,
      "close": 4.37,
      "volume": 120028634
    },
    {
      "date": "2025-12-26",
      "open": 4.36,
      "high": 4.66,
      "low": 4.26,
      "close": 4.51,
      "volume": 142116231
    },
    {
      "date": "2025-12-29",
      "open": 4.3,
      "high": 4.36,
      "low": 4.15,
      "close": 4.16,
      "volume": 112981127
    },
    {
      "date": "2025-12-30",
      "open": 4.08,
      "high": 4.12,
      "low": 3.93,
      "close": 3.98,
      "volume": 77862228
    },
    {
      "date": "2025-12-31",
      "open": 4.01,
      "high": 4.03,
      "low": 3.88,
      "close": 3.9,
      "volume": 51742712
    },
    {
      "date": "2026-01-05",
      "open": 3.87,
      "high": 3.93,
      "low": 3.83,
      "close": 3.91,
      "volume": 46373247
    },
    {
      "date": "2026-01-06",
      "open": 3.9,
      "high": 4.0,
      "low": 3.86,
      "close": 3.99,
      "volume": 59379819
    },
    {
      "date": "2026-01-07",
      "open": 3.99,
      "high": 4.06,
      "low": 3.92,
      "close": 4.02,
      "volume": 66231295
    },
    {
      "date": "2026-01-08",
      "open": 3.98,
      "high": 4.0,
      "low": 3.94,
      "close": 3.98,
      "volume": 46265951
    },
    {
      "date": "2026-01-09",
      "open": 3.98,
      "high": 4.02,
      "low": 3.95,
      "close": 4.02,
      "volume": 46585996
    },
    {
      "date": "2026-01-12",
      "open": 4.0,
      "high": 4.04,
      "low": 3.97,
      "close": 4.04,
      "volume": 51947765
    },
    {
      "date": "2026-01-13",
      "open": 4.02,
      "high": 4.07,
      "low": 3.92,
      "close": 3.94,
      "volume": 61256337
    },
    {
      "date": "2026-01-14",
      "open": 3.92,
      "high": 3.98,
      "low": 3.89,
      "close": 3.92,
      "volume": 49077669
    },
    {
      "date": "2026-01-15",
      "open": 3.92,
      "high": 3.95,
      "low": 3.84,
      "close": 3.85,
      "volume": 37913517
    },
    {
      "date": "2026-01-16",
      "open": 3.85,
      "high": 3.88,
      "low": 3.76,
      "close": 3.79,
      "volume": 30421124
    },
    {
      "date": "2026-01-19",
      "open": 3.77,
      "high": 3.87,
      "low": 3.76,
      "close": 3.87,
      "volume": 28002582
    },
    {
      "date": "2026-01-20",
      "open": 3.85,
      "high": 3.87,
      "low": 3.81,
      "close": 3.83,
      "volume": 20915626
    },
    {
      "date": "2026-01-21",
      "open": 3.81,
      "high": 3.83,
      "low": 3.77,
      "close": 3.83,
      "volume": 16548644
    },
    {
      "date": "2026-01-22",
      "open": 3.82,
      "high": 3.88,
      "low": 3.81,
      "close": 3.88,
      "volume": 19648485
    },
    {
      "date": "2026-01-23",
      "open": 3.88,
      "high": 3.98,
      "low": 3.86,
      "close": 3.95,
      "volume": 35011938
    },
    {
      "date": "2026-01-26",
      "open": 3.93,
      "high": 3.94,
      "low": 3.81,
      "close": 3.86,
      "volume": 31208564
    },
    {
      "date": "2026-01-27",
      "open": 3.84,
      "high": 3.86,
      "low": 3.76,
      "close": 3.84,
      "volume": 23100081
    },
    {
      "date": "2026-01-28",
      "open": 3.82,
      "high": 3.83,
      "low": 3.77,
      "close": 3.78,
      "volume": 20385998
    },
    {
      "date": "2026-01-29",
      "open": 3.78,
      "high": 3.83,
      "low": 3.72,
      "close": 3.81,
      "volume": 21509821
    },
    {
      "date": "2026-01-30",
      "open": 3.8,
      "high": 3.82,
      "low": 3.73,
      "close": 3.74,
      "volume": 21340310
    },
    {
      "date": "2026-02-02",
      "open": 3.75,
      "high": 3.79,
      "low": 3.72,
      "close": 3.73,
      "volume": 20729441
    },
    {
      "date": "2026-02-03",
      "open": 3.74,
      "high": 3.77,
      "low": 3.72,
      "close": 3.77,
      "volume": 16484954
    },
    {
      "date": "2026-02-04",
      "open": 3.79,
      "high": 3.88,
      "low": 3.77,
      "close": 3.87,
      "volume": 32617794
    },
    {
      "date": "2026-02-05",
      "open": 3.85,
      "high": 3.94,
      "low": 3.83,
      "close": 3.87,
      "volume": 27460387
    },
    {
      "date": "2026-02-06",
      "open": 3.84,
      "high": 3.91,
      "low": 3.83,
      "close": 3.88,
      "volume": 21084005
    },
    {
      "date": "2026-02-09",
      "open": 3.88,
      "high": 3.95,
      "low": 3.87,
      "close": 3.94,
      "volume": 27808536
    },
    {
      "date": "2026-02-10",
      "open": 3.93,
      "high": 3.93,
      "low": 3.88,
      "close": 3.88,
      "volume": 21249406
    }
  ]
}