{
  "code": "sz.000589",
  "name": "贵州轮胎",
  "industry": "",
  "area": "",
  "updated_at": "2026-02-09 21:45:59",
  "kline": [
    {
      "date": "2025-12-11",
      "open": 5.11,
      "high": 5.12,
      "low": 5.05,
      "close": 5.06,
      "volume": 22178630
    },
    {
      "date": "2025-12-12",
      "open": 5.07,
      "high": 5.13,
      "low": 5.01,
      "close": 5.03,
      "volume": 27708649
    },
    {
      "date": "2025-12-15",
      "open": 5.03,
      "high": 5.07,
      "low": 5.01,
      "close": 5.03,
      "volume": 17389158
    },
    {
      "date": "2025-12-16",
      "open": 5.05,
      "high": 5.06,
      "low": 4.96,
      "close": 4.98,
      "volume": 21188792
    },
    {
      "date": "2025-12-17",
      "open": 5.06,
      "high": 5.08,
      "low": 4.93,
      "close": 5.02,
      "volume": 20665956
    },
    {
      "date": "2025-12-18",
      "open": 5.01,
      "high": 5.09,
      "low": 4.98,
      "close": 5.06,
      "volume": 19665008
    },
    {
      "date": "2025-12-19",
      "open": 5.06,
      "high": 5.13,
      "low": 5.05,
      "close": 5.09,
      "volume": 23976339
    },
    {
      "date": "2025-12-22",
      "open": 5.11,
      "high": 5.12,
      "low": 5.06,
      "close": 5.07,
      "volume": 17582392
    },
    {
      "date": "2025-12-23",
      "open": 5.08,
      "high": 5.08,
      "low": 4.99,
      "close": 5.01,
      "volume": 23022080
    },
    {
      "date": "2025-12-24",
      "open": 5.01,
      "high": 5.04,
      "low": 4.99,
      "close": 4.99,
      "volume": 22036372
    },
    {
      "date": "2025-12-25",
      "open": 5.04,
      "high": 5.1,
      "low": 5.01,
      "close": 5.08,
      "volume": 24787539
    },
    {
      "date": "2025-12-26",
      "open": 5.09,
      "high": 5.2,
      "low": 5.08,
      "close": 5.15,
      "volume": 36270304
    },
    {
      "date": "2025-12-29",
      "open": 5.16,
      "high": 5.19,
      "low": 5.11,
      "close": 5.13,
      "volume": 22809060
    },
    {
      "date": "2025-12-30",
      "open": 5.13,
      "high": 5.31,
      "low": 5.09,
      "close": 5.23,
      "volume": 49858072
    },
    {
      "date": "2025-12-31",
      "open": 5.24,
      "high": 5.25,
      "low": 5.14,
      "close": 5.18,
      "volume": 29595513
    },
    {
      "date": "2026-01-05",
      "open": 5.18,
      "high": 5.22,
      "low": 5.14,
      "close": 5.16,
      "volume": 36236560
    },
    {
      "date": "2026-01-06",
      "open": 5.17,
      "high": 5.2,
      "low": 5.15,
      "close": 5.17,
      "volume": 31040102
    },
    {
      "date": "2026-01-07",
      "open": 5.17,
      "high": 5.2,
      "low": 5.1,
      "close": 5.11,
      "volume": 29783710
    },
    {
      "date": "2026-01-08",
      "open": 5.1,
      "high": 5.11,
      "low": 5.06,
      "close": 5.09,
      "volume": 28505718
    },
    {
      "date": "2026-01-09",
      "open": 5.07,
      "high": 5.1,
      "low": 5.04,
      "close": 5.07,
      "volume": 29311846
    },
    {
      "date": "2026-01-12",
      "open": 5.08,
      "high": 5.09,
      "low": 5.06,
      "close": 5.09,
      "volume": 28617250
    },
    {
      "date": "2026-01-13",
      "open": 5.09,
      "high": 5.1,
      "low": 5.03,
      "close": 5.05,
      "volume": 28258500
    },
    {
      "date": "2026-01-14",
      "open": 5.05,
      "high": 5.07,
      "low": 4.97,
      "close": 4.99,
      "volume": 43247760
    },
    {
      "date": "2026-01-15",
      "open": 4.99,
      "high": 5.02,
      "low": 4.96,
      "close": 4.97,
      "volume": 22744370
    },
    {
      "date": "2026-01-16",
      "open": 5.0,
      "high": 5.07,
      "low": 4.97,
      "close": 5.03,
      "volume": 30186906
    },
    {
      "date": "2026-01-19",
      "open": 5.04,
      "high": 5.18,
      "low": 5.03,
      "close": 5.15,
      "volume": 38657695
    },
    {
      "date": "2026-01-20",
      "open": 5.16,
      "high": 5.17,
      "low": 5.09,
      "close": 5.15,
      "volume": 29741404
    },
    {
      "date": "2026-01-21",
      "open": 5.13,
      "high": 5.17,
      "low": 5.11,
      "close": 5.14,
      "volume": 25401399
    },
    {
      "date": "2026-01-22",
      "open": 5.14,
      "high": 5.17,
      "low": 5.11,
      "close": 5.16,
      "volume": 25458493
    },
    {
      "date": "2026-01-23",
      "open": 5.16,
      "high": 5.18,
      "low": 5.13,
      "close": 5.15,
      "volume": 26847000
    },
    {
      "date": "2026-01-26",
      "open": 5.15,
      "high": 5.15,
      "low": 5.08,
      "close": 5.12,
      "volume": 30007823
    },
    {
      "date": "2026-01-27",
      "open": 5.11,
      "high": 5.15,
      "low": 5.04,
      "close": 5.09,
      "volume": 28781146
    },
    {
      "date": "2026-01-28",
      "open": 5.09,
      "high": 5.17,
      "low": 5.04,
      "close": 5.15,
      "volume": 33517563
    },
    {
      "date": "2026-01-29",
      "open": 5.14,
      "high": 5.15,
      "low": 5.08,
      "close": 5.11,
      "volume": 23655696
    },
    {
      "date": "2026-01-30",
      "open": 5.1,
      "high": 5.17,
      "low": 5.07,
      "close": 5.15,
      "volume": 35596095
    },
    {
      "date": "2026-02-02",
      "open": 5.12,
      "high": 5.15,
      "low": 4.96,
      "close": 4.98,
      "volume": 49370240
    },
    {
      "date": "2026-02-03",
      "open": 5.02,
      "high": 5.05,
      "low": 4.97,
      "close": 5.02,
      "volume": 25327657
    },
    {
      "date": "2026-02-04",
      "open": 5.02,
      "high": 5.18,
      "low": 5.0,
      "close": 5.17,
      "volume": 53418117
    },
    {
      "date": "2026-02-05",
      "open": 5.18,
      "high": 5.21,
      "low": 5.1,
      "close": 5.12,
      "volume": 30644886
    },
    {
      "date": "2026-02-06",
      "open": 5.12,
      "high": 5.18,
      "low": 5.08,
      "close": 5.13,
      "volume": 26741725
    },
    {
      "date": "2026-02-09",
      "open": 5.17,
      "high": 5.18,
      "low": 5.11,
      "close": 5.14,
      "volume": 23169544
    }
  ]
}