{
  "code": "sz.002151",
  "name": "北斗星通",
  "industry": "",
  "area": "",
  "updated_at": "2026-02-09 22:00:58",
  "kline": [
    {
      "date": "2025-12-11",
      "open": 32.14,
      "high": 32.6,
      "low": 31.77,
      "close": 31.8,
      "volume": 22195430
    },
    {
      "date": "2025-12-12",
      "open": 31.57,
      "high": 32.24,
      "low": 31.52,
      "close": 31.64,
      "volume": 20064374
    },
    {
      "date": "2025-12-15",
      "open": 31.54,
      "high": 32.2,
      "low": 31.14,
      "close": 31.74,
      "volume": 16623284
    },
    {
      "date": "2025-12-16",
      "open": 32.1,
      "high": 32.76,
      "low": 30.89,
      "close": 32.2,
      "volume": 29801658
    },
    {
      "date": "2025-12-17",
      "open": 32.16,
      "high": 33.0,
      "low": 31.66,
      "close": 32.12,
      "volume": 24341417
    },
    {
      "date": "2025-12-18",
      "open": 31.8,
      "high": 32.97,
      "low": 31.66,
      "close": 32.45,
      "volume": 29169644
    },
    {
      "date": "2025-12-19",
      "open": 32.37,
      "high": 33.39,
      "low": 32.31,
      "close": 33.12,
      "volume": 28631172
    },
    {
      "date": "2025-12-22",
      "open": 33.9,
      "high": 36.43,
      "low": 33.66,
      "close": 36.43,
      "volume": 30327587
    },
    {
      "date": "2025-12-23",
      "open": 36.83,
      "high": 37.52,
      "low": 34.17,
      "close": 34.45,
      "volume": 80793196
    },
    {
      "date": "2025-12-24",
      "open": 33.61,
      "high": 37.65,
      "low": 33.61,
      "close": 37.35,
      "volume": 79789417
    },
    {
      "date": "2025-12-25",
      "open": 36.5,
      "high": 39.93,
      "low": 36.46,
      "close": 38.34,
      "volume": 84004118
    },
    {
      "date": "2025-12-26",
      "open": 39.0,
      "high": 42.17,
      "low": 38.34,
      "close": 42.17,
      "volume": 114722384
    },
    {
      "date": "2025-12-29",
      "open": 41.0,
      "high": 43.2,
      "low": 40.88,
      "close": 41.72,
      "volume": 108076097
    },
    {
      "date": "2025-12-30",
      "open": 40.35,
      "high": 44.2,
      "low": 39.6,
      "close": 41.3,
      "volume": 102058616
    },
    {
      "date": "2025-12-31",
      "open": 40.33,
      "high": 45.43,
      "low": 40.33,
      "close": 45.43,
      "volume": 92749659
    },
    {
      "date": "2026-01-05",
      "open": 49.8,
      "high": 49.97,
      "low": 45.49,
      "close": 49.97,
      "volume": 118714526
    },
    {
      "date": "2026-01-06",
      "open": 49.98,
      "high": 54.97,
      "low": 49.98,
      "close": 54.97,
      "volume": 74803236
    },
    {
      "date": "2026-01-07",
      "open": 58.8,
      "high": 60.47,
      "low": 56.58,
      "close": 57.7,
      "volume": 147488686
    },
    {
      "date": "2026-01-08",
      "open": 55.88,
      "high": 62.5,
      "low": 53.95,
      "close": 59.69,
      "volume": 136867622
    },
    {
      "date": "2026-01-09",
      "open": 59.1,
      "high": 63.19,
      "low": 57.81,
      "close": 60.82,
      "volume": 121613821
    },
    {
      "date": "2026-01-12",
      "open": 62.3,
      "high": 66.9,
      "low": 60.82,
      "close": 66.9,
      "volume": 117718041
    },
    {
      "date": "2026-01-13",
      "open": 64.0,
      "high": 65.5,
      "low": 60.21,
      "close": 60.21,
      "volume": 50952917
    },
    {
      "date": "2026-01-14",
      "open": 54.3,
      "high": 60.22,
      "low": 54.19,
      "close": 54.23,
      "volume": 121626049
    },
    {
      "date": "2026-01-15",
      "open": 52.67,
      "high": 53.9,
      "low": 50.3,
      "close": 52.33,
      "volume": 103725470
    },
    {
      "date": "2026-01-16",
      "open": 52.53,
      "high": 53.2,
      "low": 49.78,
      "close": 49.93,
      "volume": 73435382
    },
    {
      "date": "2026-01-19",
      "open": 49.5,
      "high": 50.48,
      "low": 49.38,
      "close": 49.43,
      "volume": 48458989
    },
    {
      "date": "2026-01-20",
      "open": 49.43,
      "high": 49.95,
      "low": 46.69,
      "close": 47.62,
      "volume": 59555166
    },
    {
      "date": "2026-01-21",
      "open": 47.3,
      "high": 48.44,
      "low": 46.51,
      "close": 46.6,
      "volume": 37294213
    },
    {
      "date": "2026-01-22",
      "open": 46.61,
      "high": 48.0,
      "low": 46.18,
      "close": 47.54,
      "volume": 50444786
    },
    {
      "date": "2026-01-23",
      "open": 47.2,
      "high": 50.42,
      "low": 46.59,
      "close": 49.69,
      "volume": 91827937
    },
    {
      "date": "2026-01-26",
      "open": 49.0,
      "high": 49.0,
      "low": 45.02,
      "close": 45.32,
      "volume": 73102977
    },
    {
      "date": "2026-01-27",
      "open": 45.32,
      "high": 46.18,
      "low": 44.39,
      "close": 45.65,
      "volume": 39199854
    },
    {
      "date": "2026-01-28",
      "open": 45.7,
      "high": 45.85,
      "low": 44.39,
      "close": 44.63,
      "volume": 28825783
    },
    {
      "date": "2026-01-29",
      "open": 44.37,
      "high": 45.36,
      "low": 44.0,
      "close": 44.34,
      "volume": 28272279
    },
    {
      "date": "2026-01-30",
      "open": 44.29,
      "high": 44.56,
      "low": 43.15,
      "close": 43.67,
      "volume": 24824039
    },
    {
      "date": "2026-02-02",
      "open": 43.86,
      "high": 44.56,
      "low": 43.11,
      "close": 43.94,
      "volume": 23135818
    },
    {
      "date": "2026-02-03",
      "open": 43.76,
      "high": 44.98,
      "low": 43.22,
      "close": 44.75,
      "volume": 40432971
    },
    {
      "date": "2026-02-04",
      "open": 44.46,
      "high": 45.73,
      "low": 44.07,
      "close": 44.88,
      "volume": 34835528
    },
    {
      "date": "2026-02-05",
      "open": 44.0,
      "high": 44.98,
      "low": 43.77,
      "close": 44.27,
      "volume": 23955404
    },
    {
      "date": "2026-02-06",
      "open": 44.54,
      "high": 45.18,
      "low": 43.63,
      "close": 44.11,
      "volume": 29180267
    },
    {
      "date": "2026-02-09",
      "open": 44.72,
      "high": 45.11,
      "low": 44.37,
      "close": 44.99,
      "volume": 27425551
    }
  ]
}