{
  "code": "sz.000912",
  "name": "泸天化",
  "industry": "",
  "area": "",
  "updated_at": "2026-02-10 18:39:12",
  "kline": [
    {
      "date": "2025-12-11",
      "open": 4.29,
      "high": 4.3,
      "low": 4.16,
      "close": 4.18,
      "volume": 13315100
    },
    {
      "date": "2025-12-12",
      "open": 4.17,
      "high": 4.19,
      "low": 4.12,
      "close": 4.12,
      "volume": 10393909
    },
    {
      "date": "2025-12-15",
      "open": 4.12,
      "high": 4.18,
      "low": 4.1,
      "close": 4.16,
      "volume": 6625299
    },
    {
      "date": "2025-12-16",
      "open": 4.15,
      "high": 4.15,
      "low": 4.08,
      "close": 4.11,
      "volume": 8281796
    },
    {
      "date": "2025-12-17",
      "open": 4.11,
      "high": 4.14,
      "low": 4.06,
      "close": 4.13,
      "volume": 7053232
    },
    {
      "date": "2025-12-18",
      "open": 4.1,
      "high": 4.18,
      "low": 4.1,
      "close": 4.15,
      "volume": 6062200
    },
    {
      "date": "2025-12-19",
      "open": 4.16,
      "high": 4.2,
      "low": 4.14,
      "close": 4.19,
      "volume": 6200048
    },
    {
      "date": "2025-12-22",
      "open": 4.2,
      "high": 4.23,
      "low": 4.19,
      "close": 4.2,
      "volume": 6997137
    },
    {
      "date": "2025-12-23",
      "open": 4.19,
      "high": 4.21,
      "low": 4.16,
      "close": 4.17,
      "volume": 5534400
    },
    {
      "date": "2025-12-24",
      "open": 4.16,
      "high": 4.21,
      "low": 4.15,
      "close": 4.2,
      "volume": 5681815
    },
    {
      "date": "2025-12-25",
      "open": 4.19,
      "high": 4.23,
      "low": 4.18,
      "close": 4.22,
      "volume": 6363300
    },
    {
      "date": "2025-12-26",
      "open": 4.22,
      "high": 4.24,
      "low": 4.2,
      "close": 4.22,
      "volume": 7577697
    },
    {
      "date": "2025-12-29",
      "open": 4.22,
      "high": 4.23,
      "low": 4.17,
      "close": 4.19,
      "volume": 7517345
    },
    {
      "date": "2025-12-30",
      "open": 4.18,
      "high": 4.24,
      "low": 4.13,
      "close": 4.19,
      "volume": 8960700
    },
    {
      "date": "2025-12-31",
      "open": 4.19,
      "high": 4.2,
      "low": 4.1,
      "close": 4.15,
      "volume": 10465715
    },
    {
      "date": "2026-01-05",
      "open": 4.15,
      "high": 4.19,
      "low": 4.14,
      "close": 4.18,
      "volume": 6862588
    },
    {
      "date": "2026-01-06",
      "open": 4.18,
      "high": 4.28,
      "low": 4.17,
      "close": 4.26,
      "volume": 13537632
    },
    {
      "date": "2026-01-07",
      "open": 4.28,
      "high": 4.28,
      "low": 4.21,
      "close": 4.22,
      "volume": 8583900
    },
    {
      "date": "2026-01-08",
      "open": 4.21,
      "high": 4.25,
      "low": 4.2,
      "close": 4.24,
      "volume": 7327503
    },
    {
      "date": "2026-01-09",
      "open": 4.24,
      "high": 4.27,
      "low": 4.21,
      "close": 4.26,
      "volume": 12667839
    },
    {
      "date": "2026-01-12",
      "open": 4.27,
      "high": 4.29,
      "low": 4.25,
      "close": 4.28,
      "volume": 11951474
    },
    {
      "date": "2026-01-13",
      "open": 4.29,
      "high": 4.33,
      "low": 4.25,
      "close": 4.25,
      "volume": 17572176
    },
    {
      "date": "2026-01-14",
      "open": 4.25,
      "high": 4.28,
      "low": 4.19,
      "close": 4.23,
      "volume": 14724371
    },
    {
      "date": "2026-01-15",
      "open": 4.22,
      "high": 4.29,
      "low": 4.22,
      "close": 4.26,
      "volume": 8876602
    },
    {
      "date": "2026-01-16",
      "open": 4.26,
      "high": 4.28,
      "low": 4.21,
      "close": 4.23,
      "volume": 7663572
    },
    {
      "date": "2026-01-19",
      "open": 4.2,
      "high": 4.32,
      "low": 4.2,
      "close": 4.32,
      "volume": 15827520
    },
    {
      "date": "2026-01-20",
      "open": 4.33,
      "high": 4.36,
      "low": 4.3,
      "close": 4.36,
      "volume": 15175111
    },
    {
      "date": "2026-01-21",
      "open": 4.35,
      "high": 4.39,
      "low": 4.31,
      "close": 4.39,
      "volume": 13620934
    },
    {
      "date": "2026-01-22",
      "open": 4.4,
      "high": 4.5,
      "low": 4.39,
      "close": 4.48,
      "volume": 21520158
    },
    {
      "date": "2026-01-23",
      "open": 4.5,
      "high": 4.51,
      "low": 4.44,
      "close": 4.49,
      "volume": 18614976
    },
    {
      "date": "2026-01-26",
      "open": 4.49,
      "high": 4.55,
      "low": 4.46,
      "close": 4.52,
      "volume": 17796882
    },
    {
      "date": "2026-01-27",
      "open": 4.53,
      "high": 4.59,
      "low": 4.45,
      "close": 4.49,
      "volume": 17330700
    },
    {
      "date": "2026-01-28",
      "open": 4.5,
      "high": 4.64,
      "low": 4.48,
      "close": 4.6,
      "volume": 30901724
    },
    {
      "date": "2026-01-29",
      "open": 4.59,
      "high": 4.84,
      "low": 4.58,
      "close": 4.7,
      "volume": 44604999
    },
    {
      "date": "2026-01-30",
      "open": 4.64,
      "high": 4.82,
      "low": 4.62,
      "close": 4.79,
      "volume": 40908162
    },
    {
      "date": "2026-02-02",
      "open": 4.72,
      "high": 4.72,
      "low": 4.41,
      "close": 4.43,
      "volume": 31509506
    },
    {
      "date": "2026-02-03",
      "open": 4.49,
      "high": 4.59,
      "low": 4.43,
      "close": 4.58,
      "volume": 23672800
    },
    {
      "date": "2026-02-04",
      "open": 4.58,
      "high": 4.67,
      "low": 4.53,
      "close": 4.64,
      "volume": 15681005
    },
    {
      "date": "2026-02-05",
      "open": 4.63,
      "high": 4.67,
      "low": 4.57,
      "close": 4.59,
      "volume": 14059110
    },
    {
      "date": "2026-02-06",
      "open": 4.58,
      "high": 4.7,
      "low": 4.51,
      "close": 4.61,
      "volume": 12922015
    },
    {
      "date": "2026-02-09",
      "open": 4.65,
      "high": 4.7,
      "low": 4.63,
      "close": 4.68,
      "volume": 12525200
    },
    {
      "date": "2026-02-10",
      "open": 4.68,
      "high": 4.7,
      "low": 4.59,
      "close": 4.65,
      "volume": 12341800
    }
  ]
}