{
  "code": "sz.002298",
  "name": "中电鑫龙",
  "industry": "",
  "area": "",
  "updated_at": "2026-02-09 22:05:31",
  "kline": [
    {
      "date": "2025-12-11",
      "open": 10.39,
      "high": 10.42,
      "low": 10.15,
      "close": 10.16,
      "volume": 28762534
    },
    {
      "date": "2025-12-12",
      "open": 10.16,
      "high": 10.52,
      "low": 10.15,
      "close": 10.4,
      "volume": 44715811
    },
    {
      "date": "2025-12-15",
      "open": 10.28,
      "high": 10.53,
      "low": 10.26,
      "close": 10.31,
      "volume": 29720605
    },
    {
      "date": "2025-12-16",
      "open": 10.26,
      "high": 10.26,
      "low": 10.01,
      "close": 10.02,
      "volume": 34897575
    },
    {
      "date": "2025-12-17",
      "open": 10.05,
      "high": 10.19,
      "low": 9.88,
      "close": 10.16,
      "volume": 35411251
    },
    {
      "date": "2025-12-18",
      "open": 10.03,
      "high": 10.28,
      "low": 10.01,
      "close": 10.1,
      "volume": 26026403
    },
    {
      "date": "2025-12-19",
      "open": 10.11,
      "high": 10.27,
      "low": 10.1,
      "close": 10.26,
      "volume": 27921735
    },
    {
      "date": "2025-12-22",
      "open": 10.3,
      "high": 10.43,
      "low": 10.25,
      "close": 10.37,
      "volume": 24209235
    },
    {
      "date": "2025-12-23",
      "open": 10.34,
      "high": 10.34,
      "low": 10.15,
      "close": 10.19,
      "volume": 24967402
    },
    {
      "date": "2025-12-24",
      "open": 10.23,
      "high": 10.55,
      "low": 10.18,
      "close": 10.49,
      "volume": 46913816
    },
    {
      "date": "2025-12-25",
      "open": 10.49,
      "high": 10.52,
      "low": 10.36,
      "close": 10.49,
      "volume": 31948943
    },
    {
      "date": "2025-12-26",
      "open": 10.48,
      "high": 10.57,
      "low": 10.38,
      "close": 10.48,
      "volume": 38709656
    },
    {
      "date": "2025-12-29",
      "open": 10.43,
      "high": 10.57,
      "low": 10.42,
      "close": 10.47,
      "volume": 28923521
    },
    {
      "date": "2025-12-30",
      "open": 10.42,
      "high": 10.56,
      "low": 10.33,
      "close": 10.45,
      "volume": 30096352
    },
    {
      "date": "2025-12-31",
      "open": 10.46,
      "high": 10.52,
      "low": 10.25,
      "close": 10.44,
      "volume": 32036306
    },
    {
      "date": "2026-01-05",
      "open": 10.47,
      "high": 10.93,
      "low": 10.45,
      "close": 10.9,
      "volume": 72315006
    },
    {
      "date": "2026-01-06",
      "open": 10.9,
      "high": 11.06,
      "low": 10.77,
      "close": 10.98,
      "volume": 61565643
    },
    {
      "date": "2026-01-07",
      "open": 11.05,
      "high": 11.15,
      "low": 10.84,
      "close": 10.87,
      "volume": 53637714
    },
    {
      "date": "2026-01-08",
      "open": 10.86,
      "high": 11.15,
      "low": 10.82,
      "close": 11.09,
      "volume": 56532197
    },
    {
      "date": "2026-01-09",
      "open": 11.05,
      "high": 11.3,
      "low": 11.01,
      "close": 11.22,
      "volume": 57938821
    },
    {
      "date": "2026-01-12",
      "open": 11.34,
      "high": 11.64,
      "low": 11.29,
      "close": 11.64,
      "volume": 85597174
    },
    {
      "date": "2026-01-13",
      "open": 11.82,
      "high": 12.78,
      "low": 11.18,
      "close": 12.2,
      "volume": 168154787
    },
    {
      "date": "2026-01-14",
      "open": 12.18,
      "high": 12.67,
      "low": 11.79,
      "close": 12.03,
      "volume": 129249079
    },
    {
      "date": "2026-01-15",
      "open": 11.89,
      "high": 12.4,
      "low": 11.4,
      "close": 12.01,
      "volume": 99174957
    },
    {
      "date": "2026-01-16",
      "open": 12.55,
      "high": 12.56,
      "low": 11.68,
      "close": 11.69,
      "volume": 91547953
    },
    {
      "date": "2026-01-19",
      "open": 11.51,
      "high": 12.05,
      "low": 11.41,
      "close": 11.9,
      "volume": 67733279
    },
    {
      "date": "2026-01-20",
      "open": 11.91,
      "high": 12.12,
      "low": 11.72,
      "close": 11.82,
      "volume": 57274302
    },
    {
      "date": "2026-01-21",
      "open": 11.58,
      "high": 11.62,
      "low": 11.31,
      "close": 11.33,
      "volume": 63819552
    },
    {
      "date": "2026-01-22",
      "open": 11.36,
      "high": 11.43,
      "low": 11.27,
      "close": 11.34,
      "volume": 34349668
    },
    {
      "date": "2026-01-23",
      "open": 11.34,
      "high": 11.55,
      "low": 11.25,
      "close": 11.52,
      "volume": 43853134
    },
    {
      "date": "2026-01-26",
      "open": 11.55,
      "high": 11.6,
      "low": 11.1,
      "close": 11.14,
      "volume": 43333621
    },
    {
      "date": "2026-01-27",
      "open": 11.1,
      "high": 11.13,
      "low": 10.65,
      "close": 10.96,
      "volume": 41140019
    },
    {
      "date": "2026-01-28",
      "open": 10.96,
      "high": 11.09,
      "low": 10.76,
      "close": 10.77,
      "volume": 28584543
    },
    {
      "date": "2026-01-29",
      "open": 10.68,
      "high": 11.0,
      "low": 10.53,
      "close": 10.76,
      "volume": 32025314
    },
    {
      "date": "2026-01-30",
      "open": 10.85,
      "high": 10.85,
      "low": 10.34,
      "close": 10.41,
      "volume": 31012480
    },
    {
      "date": "2026-02-02",
      "open": 10.26,
      "high": 10.68,
      "low": 10.26,
      "close": 10.34,
      "volume": 30872774
    },
    {
      "date": "2026-02-03",
      "open": 10.49,
      "high": 10.56,
      "low": 10.31,
      "close": 10.56,
      "volume": 24220347
    },
    {
      "date": "2026-02-04",
      "open": 10.51,
      "high": 10.67,
      "low": 10.44,
      "close": 10.57,
      "volume": 22093205
    },
    {
      "date": "2026-02-05",
      "open": 10.58,
      "high": 10.58,
      "low": 10.28,
      "close": 10.3,
      "volume": 22938641
    },
    {
      "date": "2026-02-06",
      "open": 10.26,
      "high": 10.53,
      "low": 10.18,
      "close": 10.45,
      "volume": 21675975
    },
    {
      "date": "2026-02-09",
      "open": 10.58,
      "high": 10.72,
      "low": 10.53,
      "close": 10.69,
      "volume": 23531344
    }
  ]
}