{
  "code": "sz.159316",
  "name": "易方达恒生港股通创新药ETF",
  "industry": "",
  "area": "",
  "updated_at": "2026-02-09 22:31:49",
  "kline": [
    {
      "date": "2026-01-05",
      "open": 1.259,
      "high": 1.325,
      "low": 1.259,
      "close": 1.325,
      "volume": 490748025
    },
    {
      "date": "2026-01-06",
      "open": 1.327,
      "high": 1.333,
      "low": 1.313,
      "close": 1.329,
      "volume": 407793520
    },
    {
      "date": "2026-01-07",
      "open": 1.333,
      "high": 1.376,
      "low": 1.333,
      "close": 1.37,
      "volume": 529143553
    },
    {
      "date": "2026-01-08",
      "open": 1.385,
      "high": 1.402,
      "low": 1.374,
      "close": 1.38,
      "volume": 394994580
    },
    {
      "date": "2026-01-09",
      "open": 1.368,
      "high": 1.395,
      "low": 1.356,
      "close": 1.394,
      "volume": 423843967
    },
    {
      "date": "2026-01-12",
      "open": 1.395,
      "high": 1.405,
      "low": 1.373,
      "close": 1.384,
      "volume": 505327900
    },
    {
      "date": "2026-01-13",
      "open": 1.397,
      "high": 1.429,
      "low": 1.386,
      "close": 1.39,
      "volume": 576431800
    },
    {
      "date": "2026-01-14",
      "open": 1.416,
      "high": 1.433,
      "low": 1.388,
      "close": 1.409,
      "volume": 541663569
    },
    {
      "date": "2026-01-15",
      "open": 1.409,
      "high": 1.423,
      "low": 1.395,
      "close": 1.4,
      "volume": 329824111
    },
    {
      "date": "2026-01-16",
      "open": 1.397,
      "high": 1.408,
      "low": 1.384,
      "close": 1.387,
      "volume": 305150068
    },
    {
      "date": "2026-01-19",
      "open": 1.38,
      "high": 1.386,
      "low": 1.346,
      "close": 1.353,
      "volume": 302189800
    },
    {
      "date": "2026-01-20",
      "open": 1.35,
      "high": 1.362,
      "low": 1.335,
      "close": 1.341,
      "volume": 295414400
    },
    {
      "date": "2026-01-21",
      "open": 1.341,
      "high": 1.35,
      "low": 1.33,
      "close": 1.334,
      "volume": 241828500
    },
    {
      "date": "2026-01-22",
      "open": 1.348,
      "high": 1.354,
      "low": 1.319,
      "close": 1.322,
      "volume": 190751300
    },
    {
      "date": "2026-01-23",
      "open": 1.329,
      "high": 1.35,
      "low": 1.326,
      "close": 1.343,
      "volume": 307570802
    },
    {
      "date": "2026-01-26",
      "open": 1.34,
      "high": 1.34,
      "low": 1.313,
      "close": 1.316,
      "volume": 328529383
    },
    {
      "date": "2026-01-27",
      "open": 1.318,
      "high": 1.333,
      "low": 1.303,
      "close": 1.323,
      "volume": 270958900
    },
    {
      "date": "2026-01-28",
      "open": 1.326,
      "high": 1.346,
      "low": 1.32,
      "close": 1.344,
      "volume": 302127100
    },
    {
      "date": "2026-01-29",
      "open": 1.34,
      "high": 1.351,
      "low": 1.332,
      "close": 1.334,
      "volume": 274494800
    },
    {
      "date": "2026-01-30",
      "open": 1.336,
      "high": 1.348,
      "low": 1.305,
      "close": 1.306,
      "volume": 320991900
    },
    {
      "date": "2026-02-02",
      "open": 1.305,
      "high": 1.306,
      "low": 1.257,
      "close": 1.26,
      "volume": 278238400
    },
    {
      "date": "2026-02-03",
      "open": 1.27,
      "high": 1.284,
      "low": 1.246,
      "close": 1.284,
      "volume": 314566890
    },
    {
      "date": "2026-02-04",
      "open": 1.28,
      "high": 1.302,
      "low": 1.258,
      "close": 1.298,
      "volume": 292601877
    },
    {
      "date": "2026-02-05",
      "open": 1.281,
      "high": 1.3,
      "low": 1.271,
      "close": 1.284,
      "volume": 317377438
    },
    {
      "date": "2026-02-06",
      "open": 1.274,
      "high": 1.304,
      "low": 1.268,
      "close": 1.296,
      "volume": 319336100
    },
    {
      "date": "2026-02-09",
      "open": 1.31,
      "high": 1.327,
      "low": 1.305,
      "close": 1.313,
      "volume": 268947201
    }
  ]
}