{
  "code": "sz.159333",
  "name": "万家中证港股通央企红利ETF",
  "industry": "",
  "area": "",
  "updated_at": "2026-02-09 22:32:14",
  "kline": [
    {
      "date": "2026-01-05",
      "open": 1.408,
      "high": 1.415,
      "low": 1.408,
      "close": 1.41,
      "volume": 8617000
    },
    {
      "date": "2026-01-06",
      "open": 1.413,
      "high": 1.423,
      "low": 1.411,
      "close": 1.422,
      "volume": 12070400
    },
    {
      "date": "2026-01-07",
      "open": 1.422,
      "high": 1.427,
      "low": 1.415,
      "close": 1.418,
      "volume": 5107900
    },
    {
      "date": "2026-01-08",
      "open": 1.418,
      "high": 1.421,
      "low": 1.408,
      "close": 1.412,
      "volume": 5419900
    },
    {
      "date": "2026-01-09",
      "open": 1.416,
      "high": 1.42,
      "low": 1.409,
      "close": 1.414,
      "volume": 10718800
    },
    {
      "date": "2026-01-12",
      "open": 1.419,
      "high": 1.419,
      "low": 1.405,
      "close": 1.414,
      "volume": 10028204
    },
    {
      "date": "2026-01-13",
      "open": 1.415,
      "high": 1.43,
      "low": 1.415,
      "close": 1.423,
      "volume": 38499311
    },
    {
      "date": "2026-01-14",
      "open": 1.423,
      "high": 1.427,
      "low": 1.413,
      "close": 1.417,
      "volume": 19334000
    },
    {
      "date": "2026-01-15",
      "open": 1.418,
      "high": 1.423,
      "low": 1.411,
      "close": 1.414,
      "volume": 8100700
    },
    {
      "date": "2026-01-16",
      "open": 1.418,
      "high": 1.424,
      "low": 1.404,
      "close": 1.405,
      "volume": 9788500
    },
    {
      "date": "2026-01-19",
      "open": 1.405,
      "high": 1.413,
      "low": 1.399,
      "close": 1.405,
      "volume": 10499600
    },
    {
      "date": "2026-01-20",
      "open": 1.402,
      "high": 1.41,
      "low": 1.396,
      "close": 1.408,
      "volume": 11479900
    },
    {
      "date": "2026-01-21",
      "open": 1.408,
      "high": 1.412,
      "low": 1.401,
      "close": 1.403,
      "volume": 5828500
    },
    {
      "date": "2026-01-22",
      "open": 1.403,
      "high": 1.416,
      "low": 1.403,
      "close": 1.413,
      "volume": 9338800
    },
    {
      "date": "2026-01-23",
      "open": 1.413,
      "high": 1.416,
      "low": 1.401,
      "close": 1.402,
      "volume": 13322800
    },
    {
      "date": "2026-01-26",
      "open": 1.405,
      "high": 1.425,
      "low": 1.402,
      "close": 1.418,
      "volume": 21189900
    },
    {
      "date": "2026-01-27",
      "open": 1.419,
      "high": 1.434,
      "low": 1.39,
      "close": 1.433,
      "volume": 24706101
    },
    {
      "date": "2026-01-28",
      "open": 1.435,
      "high": 1.462,
      "low": 1.432,
      "close": 1.459,
      "volume": 14615200
    },
    {
      "date": "2026-01-29",
      "open": 1.459,
      "high": 1.475,
      "low": 1.457,
      "close": 1.473,
      "volume": 15666200
    },
    {
      "date": "2026-01-30",
      "open": 1.479,
      "high": 1.482,
      "low": 1.448,
      "close": 1.454,
      "volume": 14344100
    },
    {
      "date": "2026-02-02",
      "open": 1.443,
      "high": 1.445,
      "low": 1.411,
      "close": 1.42,
      "volume": 23881700
    },
    {
      "date": "2026-02-03",
      "open": 1.421,
      "high": 1.444,
      "low": 1.42,
      "close": 1.436,
      "volume": 14390100
    },
    {
      "date": "2026-02-04",
      "open": 1.432,
      "high": 1.459,
      "low": 1.431,
      "close": 1.459,
      "volume": 8382900
    },
    {
      "date": "2026-02-05",
      "open": 1.457,
      "high": 1.457,
      "low": 1.437,
      "close": 1.449,
      "volume": 9278700
    },
    {
      "date": "2026-02-06",
      "open": 1.447,
      "high": 1.457,
      "low": 1.434,
      "close": 1.448,
      "volume": 6813000
    },
    {
      "date": "2026-02-09",
      "open": 1.454,
      "high": 1.469,
      "low": 1.454,
      "close": 1.463,
      "volume": 11982700
    }
  ]
}