{
  "code": "sz.300055",
  "name": "万邦达",
  "industry": "",
  "area": "",
  "updated_at": "2026-02-09 22:57:27",
  "kline": [
    {
      "date": "2025-12-11",
      "open": 7.99,
      "high": 8.02,
      "low": 7.87,
      "close": 7.87,
      "volume": 9240632
    },
    {
      "date": "2025-12-12",
      "open": 7.9,
      "high": 7.95,
      "low": 7.71,
      "close": 7.77,
      "volume": 7980300
    },
    {
      "date": "2025-12-15",
      "open": 7.71,
      "high": 7.82,
      "low": 7.69,
      "close": 7.78,
      "volume": 6394963
    },
    {
      "date": "2025-12-16",
      "open": 7.78,
      "high": 7.83,
      "low": 7.38,
      "close": 7.41,
      "volume": 12872000
    },
    {
      "date": "2025-12-17",
      "open": 7.41,
      "high": 7.6,
      "low": 7.29,
      "close": 7.51,
      "volume": 12337305
    },
    {
      "date": "2025-12-18",
      "open": 7.5,
      "high": 7.59,
      "low": 7.4,
      "close": 7.41,
      "volume": 6976006
    },
    {
      "date": "2025-12-19",
      "open": 7.42,
      "high": 7.52,
      "low": 7.4,
      "close": 7.5,
      "volume": 6325354
    },
    {
      "date": "2025-12-22",
      "open": 7.49,
      "high": 7.58,
      "low": 7.47,
      "close": 7.5,
      "volume": 5804300
    },
    {
      "date": "2025-12-23",
      "open": 7.48,
      "high": 7.52,
      "low": 7.37,
      "close": 7.43,
      "volume": 6866850
    },
    {
      "date": "2025-12-24",
      "open": 7.42,
      "high": 7.44,
      "low": 7.35,
      "close": 7.39,
      "volume": 5946527
    },
    {
      "date": "2025-12-25",
      "open": 7.35,
      "high": 7.47,
      "low": 7.34,
      "close": 7.43,
      "volume": 6519179
    },
    {
      "date": "2025-12-26",
      "open": 7.43,
      "high": 7.9,
      "low": 7.4,
      "close": 7.75,
      "volume": 18309510
    },
    {
      "date": "2025-12-29",
      "open": 7.8,
      "high": 7.85,
      "low": 7.58,
      "close": 7.61,
      "volume": 11831111
    },
    {
      "date": "2025-12-30",
      "open": 7.6,
      "high": 8.24,
      "low": 7.53,
      "close": 8.03,
      "volume": 31074765
    },
    {
      "date": "2025-12-31",
      "open": 8.17,
      "high": 8.17,
      "low": 7.97,
      "close": 8.15,
      "volume": 17605433
    },
    {
      "date": "2026-01-05",
      "open": 8.25,
      "high": 8.5,
      "low": 7.9,
      "close": 8.07,
      "volume": 29779143
    },
    {
      "date": "2026-01-06",
      "open": 8.13,
      "high": 8.27,
      "low": 7.91,
      "close": 7.94,
      "volume": 20280003
    },
    {
      "date": "2026-01-07",
      "open": 7.91,
      "high": 8.11,
      "low": 7.84,
      "close": 8.02,
      "volume": 14464933
    },
    {
      "date": "2026-01-08",
      "open": 7.94,
      "high": 8.24,
      "low": 7.91,
      "close": 8.13,
      "volume": 18441277
    },
    {
      "date": "2026-01-09",
      "open": 8.13,
      "high": 8.24,
      "low": 7.98,
      "close": 8.06,
      "volume": 15839404
    },
    {
      "date": "2026-01-12",
      "open": 8.09,
      "high": 8.11,
      "low": 7.93,
      "close": 8.11,
      "volume": 14742130
    },
    {
      "date": "2026-01-13",
      "open": 8.04,
      "high": 8.39,
      "low": 8.02,
      "close": 8.19,
      "volume": 21777000
    },
    {
      "date": "2026-01-14",
      "open": 8.18,
      "high": 8.2,
      "low": 7.91,
      "close": 8.01,
      "volume": 19700633
    },
    {
      "date": "2026-01-15",
      "open": 8.08,
      "high": 8.08,
      "low": 7.93,
      "close": 7.99,
      "volume": 7560891
    },
    {
      "date": "2026-01-16",
      "open": 8.03,
      "high": 8.12,
      "low": 7.86,
      "close": 7.9,
      "volume": 11297774
    },
    {
      "date": "2026-01-19",
      "open": 7.9,
      "high": 8.15,
      "low": 7.86,
      "close": 8.15,
      "volume": 15119398
    },
    {
      "date": "2026-01-20",
      "open": 8.13,
      "high": 8.16,
      "low": 7.91,
      "close": 7.96,
      "volume": 10981129
    },
    {
      "date": "2026-01-21",
      "open": 7.92,
      "high": 8.18,
      "low": 7.92,
      "close": 8.16,
      "volume": 14810152
    },
    {
      "date": "2026-01-22",
      "open": 8.16,
      "high": 8.26,
      "low": 8.1,
      "close": 8.19,
      "volume": 12434172
    },
    {
      "date": "2026-01-23",
      "open": 8.2,
      "high": 8.35,
      "low": 8.18,
      "close": 8.28,
      "volume": 13843975
    },
    {
      "date": "2026-01-26",
      "open": 8.25,
      "high": 8.31,
      "low": 7.96,
      "close": 8.17,
      "volume": 19353781
    },
    {
      "date": "2026-01-27",
      "open": 8.15,
      "high": 8.35,
      "low": 7.9,
      "close": 8.35,
      "volume": 25511501
    },
    {
      "date": "2026-01-28",
      "open": 8.4,
      "high": 8.4,
      "low": 8.01,
      "close": 8.06,
      "volume": 26019888
    },
    {
      "date": "2026-01-29",
      "open": 8.06,
      "high": 8.13,
      "low": 7.81,
      "close": 7.94,
      "volume": 21622400
    },
    {
      "date": "2026-01-30",
      "open": 7.87,
      "high": 7.94,
      "low": 7.71,
      "close": 7.79,
      "volume": 13018624
    },
    {
      "date": "2026-02-02",
      "open": 7.57,
      "high": 7.75,
      "low": 7.27,
      "close": 7.55,
      "volume": 17736496
    },
    {
      "date": "2026-02-03",
      "open": 7.55,
      "high": 7.67,
      "low": 7.52,
      "close": 7.57,
      "volume": 9198881
    },
    {
      "date": "2026-02-04",
      "open": 7.62,
      "high": 7.65,
      "low": 7.52,
      "close": 7.56,
      "volume": 8524900
    },
    {
      "date": "2026-02-05",
      "open": 7.5,
      "high": 7.58,
      "low": 7.39,
      "close": 7.4,
      "volume": 7809401
    },
    {
      "date": "2026-02-06",
      "open": 7.39,
      "high": 7.57,
      "low": 7.31,
      "close": 7.42,
      "volume": 8138778
    },
    {
      "date": "2026-02-09",
      "open": 7.52,
      "high": 8.24,
      "low": 7.52,
      "close": 8.18,
      "volume": 37454229
    }
  ]
}